pdftoprompt/__init__.py
pdftoprompt/compressor.py
pdftoprompt-0.1.2.dist-info/METADATA
pdftoprompt-0.1.2.dist-info/WHEEL
pdftoprompt-0.1.2.dist-info/RECORD
