Metadata-Version: 2.1
Name: pdftoprompt
Version: 0.1.2
Summary: Python library to abbreviate a PDF file to GPT 8k prompt length
Author: Christopher Carroll Smith
Author-email: chriscarrollsmith@gmail.com
Requires-Python: >=3.9,<4.0
Classifier: Programming Language :: Python :: 3
Classifier: Programming Language :: Python :: 3.9
Classifier: Programming Language :: Python :: 3.10
Classifier: Programming Language :: Python :: 3.11
Requires-Dist: openai (>=0.27.4,<0.28.0)
Requires-Dist: pdf2image (>=1.16.3,<2.0.0)
Requires-Dist: pypdf (>=3.7.0,<4.0.0)
Requires-Dist: pytesseract (>=0.3.10,<0.4.0)
Requires-Dist: python-dotenv (>=1.0.0,<2.0.0)
Requires-Dist: requests (>=2.28.2,<3.0.0)
